gitlab_client/base.py
abedy_gitlab_client-0.3.dist-info/METADATA
abedy_gitlab_client-0.3.dist-info/WHEEL
abedy_gitlab_client-0.3.dist-info/RECORD
